README.md
setup.py
bunnings_search_results_scraper/__init__.py
bunnings_search_results_scraper.egg-info/PKG-INFO
bunnings_search_results_scraper.egg-info/SOURCES.txt
bunnings_search_results_scraper.egg-info/dependency_links.txt
bunnings_search_results_scraper.egg-info/requires.txt
bunnings_search_results_scraper.egg-info/top_level.txt